crossplane/pythonic/__about__.py
crossplane/pythonic/__init__.py
crossplane/pythonic/__main__.py
crossplane/pythonic/auto_ready.py
crossplane/pythonic/command.py
crossplane/pythonic/composite.py
crossplane/pythonic/function.py
crossplane/pythonic/grpc.py
crossplane/pythonic/main.py
crossplane/pythonic/packages.py
crossplane/pythonic/protobuf.py
crossplane/pythonic/render.py
crossplane/pythonic/version.py
crossplane_function_pythonic-0.3.1.dist-info/METADATA
crossplane_function_pythonic-0.3.1.dist-info/WHEEL
crossplane_function_pythonic-0.3.1.dist-info/entry_points.txt
crossplane_function_pythonic-0.3.1.dist-info/licenses/LICENSE
crossplane_function_pythonic-0.3.1.dist-info/RECORD
