Metadata-Version: 2.4
Name: crossplane-function-pythonic
Version: 0.3.1
Summary: A Python centric Crossplane Function
Project-URL: Documentation, https://github.com/crossplane-contrib/function-pythonic#readme
Project-URL: Issues, https://github.com/crossplane-contrib/function-pythonic/issues
Project-URL: Source, https://github.com/crossplane-contrib/function-pythonic
Author-email: Patrick J McNerthney <pat@mcnerthney.com>
License-Expression: Apache-2.0
License-File: LICENSE
Classifier: Development Status :: 4 - Beta
Classifier: Programming Language :: Python
Classifier: Programming Language :: Python :: 3.12
Classifier: Programming Language :: Python :: 3.13
Classifier: Programming Language :: Python :: 3.14
Requires-Python: <3.15,>=3.12
Requires-Dist: crossplane-function-sdk-python==0.10.0
Requires-Dist: pyyaml==6.0.3
Provides-Extra: packages
Requires-Dist: kopf==1.40.1; extra == 'packages'
Provides-Extra: pip-install
Requires-Dist: pip==25.3; extra == 'pip-install'
